snowball/bootstrapping.py
snowball/cli.py
snowball/commons.py
snowball/config.py
snowball/pattern.py
snowball/reverb_breds.py
snowball/seed.py
snowball/sentence.py
snowball/snowball_tuple.py
snowball/vector_space_model.py
snowball_extractor-1.0.5.dist-info/LICENSE
snowball_extractor-1.0.5.dist-info/METADATA
snowball_extractor-1.0.5.dist-info/WHEEL
snowball_extractor-1.0.5.dist-info/entry_points.txt
snowball_extractor-1.0.5.dist-info/top_level.txt
snowball_extractor-1.0.5.dist-info/RECORD
